Metadata-Version: 1.0
Name: hyperdual
Version: 0.8.1
Summary: HyperDual Number Library
Home-page: UNKNOWN
Author: UNKNOWN
Author-email: UNKNOWN
License: UNKNOWN
Platform: UNKNOWN
